{"otherData":{},"traceEvents":[{"cat":"function","dur":0,"name":"GlfwWindow.__init__","ph":"X","pid":0,"tid":"MainThread (968)","ts":1612291553},{"cat":"function","dur":0.004000186920166016,"name":"Shader.AddStage","ph":"X","pid":0,"tid":"MainThread (968)","ts":1612291553.8794887},{"cat":"function","dur":0.0010001659393310547,"name":"Shader.AddStage","ph":"X","pid":0,"tid":"MainThread (968)","ts":1612291553.883489},{"cat":"function","dur":0.0009999275207519531,"name":"Shader.Compile","ph":"X","pid":0,"tid":"MainThread (968)","ts":1612291553.884489},{"cat":"function","dur":0.01500082015991211,"name":"BasicRenderer.__init__","ph":"X","pid":0,"tid":"MainThread (968)","ts":1612291553.8794887},{"cat":"function","dur":0.0010001659393310547,"name":"Shader.AddStage","ph":"X","pid":0,"tid":"MainThread (968)","ts":1612291553.8944895},{"cat":"function","dur":0.0,"name":"Shader.AddStage","ph":"X","pid":0,"tid":"MainThread (968)","ts":1612291553.8954897},{"cat":"function","dur":0.0010001659393310547,"name":"Shader.Compile","ph":"X","pid":0,"tid":"MainThread (968)","ts":1612291553.8954897},{"cat":"function","dur":0.0030002593994140625,"name":"TextRenderer.__init__","ph":"X","pid":0,"tid":"MainThread (968)","ts":1612291553.8944895},{"cat":"function","dur":0.0,"name":"Shader.AddStage","ph":"X","pid":0,"tid":"MainThread (968)","ts":1612291553.8974898},{"cat":"function","dur":0.0010001659393310547,"name":"Shader.AddStage","ph":"X","pid":0,"tid":"MainThread (968)","ts":1612291553.8974898},{"cat":"function","dur":0.0,"name":"Shader.Compile","ph":"X","pid":0,"tid":"MainThread (968)","ts":1612291553.89849},{"cat":"function","dur":0.0009999275207519531,"name":"Shader.AddStage","ph":"X","pid":0,"tid":"MainThread (968)","ts":1612291553.89849},{"cat":"function","dur":0.0,"name":"Shader.AddStage","ph":"X","pid":0,"tid":"MainThread (968)","ts":1612291553.8994899},{"cat":"function","dur":0.0010001659393310547,"name":"Shader.AddStage","ph":"X","pid":0,"tid":"MainThread (968)","ts":1612291553.8994899},{"cat":"function","dur":0.0,"name":"Shader.Compile","ph":"X","pid":0,"tid":"MainThread (968)","ts":1612291553.90049},{"cat":"function","dur":0.0,"name":"Shader.AddStage","ph":"X","pid":0,"tid":"MainThread (968)","ts":1612291553.90149},{"cat":"function","dur":0.0010001659393310547,"name":"Shader.AddStage","ph":"X","pid":0,"tid":"MainThread (968)","ts":1612291553.90149},{"cat":"function","dur":0.0,"name":"Shader.Compile","ph":"X","pid":0,"tid":"MainThread (968)","ts":1612291553.9024901},{"cat":"function","dur":0.02500152587890625,"name":"Renderer.Initialize","ph":"X","pid":0,"tid":"MainThread (968)","ts":1612291553.8794887},{"cat":"function","dur":0.014000892639160156,"name":"TextureArray.__init__","ph":"X","pid":0,"tid":"MainThread (968)","ts":1612291556.5847466},{"cat":"function","dur":0.3540201187133789,"name":"TextureArray.UploadTexture","ph":"X","pid":0,"tid":"MainThread (968)","ts":1612291556.7017534},{"cat":"function","dur":0,"name":"GlfwWindow.OnLoad","ph":"X","pid":0,"tid":"MainThread (968)","ts":1612291553}